how_freedom_feels/__init__.py
how_freedom_feels/cli.py
how_freedom_feels/core.py
how_freedom_feels-0.1.7.dist-info/licenses/LICENSE
how_freedom_feels-0.1.7.dist-info/METADATA
how_freedom_feels-0.1.7.dist-info/WHEEL
how_freedom_feels-0.1.7.dist-info/entry_points.txt
how_freedom_feels-0.1.7.dist-info/top_level.txt
how_freedom_feels-0.1.7.dist-info/RECORD
