Metadata-Version: 2.4
Name: how-freedom-feels
Version: 0.1.7
Summary: A VPN connection manager with custom config support
Home-page: https://github.com/guider23/how-freedom-feels
Author: Siddarth
Author-email: Siddarth <sofiyasenthilkumar@gmail.com>
License-Expression: MIT
Project-URL: Homepage, https://github.com/guider23/how-freedom-feels
Classifier: Programming Language :: Python :: 3
Classifier: Programming Language :: Python :: 3.7
Classifier: Programming Language :: Python :: 3.8
Classifier: Programming Language :: Python :: 3.9
Classifier: Programming Language :: Python :: 3.10
Classifier: Programming Language :: Python :: 3.11
Classifier: Operating System :: OS Independent
Requires-Python: >=3.7
License-File: LICENSE
Requires-Dist: requests>=2.25.0
Requires-Dist: click>=8.0.0
Dynamic: author
Dynamic: home-page
Dynamic: license-file
Dynamic: requires-python
